{"name":"gnar","counters":[{"type":"extreme","champName":"irelia","description":"irelia has so many options to close the gap against you. the key here is to keep an eye on your minions that are low on health. irelia’s q will reset if she kills a minion with it. you absolutely have to dodge her e because it applies her mark on you. overall, you want irelia to push in this matchup as much as possible. keep your minion wave close to your tower and ask for ganks."},{"type":"major","champName":"yasuo","description":"yasuo is an absolute nightmare for gnar. his e can be used indefinitely as long as he has minions to use it on. because of this, gnar’s only option to stay at a range is to step far from his own minion wave. the best time to trade with yasuo is when he has no minions to e through. watch carefully for when yasuo has his tornado. yasuo’s w will eat gnar’s q and put it on the full cooldown. it’ll also stop mega gnar’s q from travelling. rush ninja tabi."}],"synergies":[{"type":"ideal","champName":"jarvan iv"},{"type":"ideal","champName":"amumu"},{"type":"ideal","champName":"orianna"},{"type":"strong","champName":"gragas"},{"type":"ideal","champName":"jarvan iv"},{"type":"ideal","champName":"amumu"},{"type":"ideal","champName":"orianna"},{"type":"strong","champName":"gragas"}],"archetype":["specialist"],"lines":[]}