{"name":"jhin","counters":[{"type":"extreme","champName":"draven","description":"perma ban."},{"type":"extreme","champName":"ashe","description":"the matchup is really hard but i have lot of data for you :"},{"type":"extreme","champName":"kalista","description":"same kind of draven but less played and less strong, remember that if at 15min you are both 0/0/0 you won."},{"type":"extreme","champName":"nilah","description":"play like it is a samira, but less strong in ealy."},{"type":"extreme","champName":"yasuo","description":"it's very rare to face one, so it's not a big deal, but yasuo is the biggest counter to jhin in lane, just so you know."},{"type":"major","champName":"lucian","description":"skilled matchup but he has better trades also depend a lot of supports"},{"type":"major","champName":"samira","description":"depend a lot of supports but keep desitance her all in destroy jhin"},{"type":"major","champName":"jinx","description":"really easy in lane, but she outscale jhin by far. so do your best to get early advantage"},{"type":"major","champName":"kog'maw","description":"honestly i don't figure out why it's hard, depends of meta and supports but atm it's hard in lane overall"}],"synergies":[{"type":"ideal","champName":"zyra","description":"best support of all time for jhin remember : in this section i'll only note the lane power, not the winrate if you want to see win rate with supports go on websites like league of graph"},{"type":"ideal","champName":"vel'koz","description":"best support atm for jhin"},{"type":"ideal","champName":"neeko","description":"also really good, she has the damages and cc you want"},{"type":"ideal","champName":"lux","description":"same as neeko, cc and damages thats what you want"},{"type":"ideal","champName":"karma","description":"peel + damage + mobility"},{"type":"ideal","champName":"pyke","description":"even if his r don't fit well with jhin, the agreesivity of thoses 2 guys is insane together, easy lane"},{"type":"ideal","champName":"xerath","description":"insane damages and range perfect for jhin"},{"type":"strong","champName":"seraphine","description":"kind of a karma, less good but insane laning"},{"type":"strong","champName":"nautilus","description":"really strong, he lack of damages but insane cc allow you to deal a lot"},{"type":"strong","champName":"blitzcrank","description":"blitz wants to have prio in lane, you are the man for this"},{"type":"strong","champName":"thresh","description":"gives you mobility and insane peel, not really agressive but same kind of nautilus good lane"},{"type":"strong","champName":"leona","description":"nice peel, nice lane"},{"type":"strong","champName":"swain","description":"good damages not the best at this job be strong"},{"type":"strong","champName":"pantheon","description":"extreme agressive, one shot every adc, but not always good can be zoned to hard by karma or this kind of champ"},{"type":"ok","champName":"soraka","description":"might lack of dmg to kill but really safe"},{"type":"ok","champName":"hwei","description":"can be strong against weak laners that you can hard poke, but not the best at the job"},{"type":"ok","champName":"morgana","description":"really confortable to play with, btw don't instant w on cages, wait 2s to click"},{"type":"ok","champName":"ashe","description":"she has slow and damages, its good but you are weak af"},{"type":"ok","champName":"taric","description":"not really good in lane but really nice in late and mid"},{"type":"ok","champName":"brand","description":"jhin needs damages but not that much, still ok"},{"type":"ok","champName":"alistar","description":"play under turret that what ali wants, not insane but good peel and dives"},{"type":"ok","champName":"camille","description":"its flip it, can be s tier or d tier depends of the enemy support but"},{"type":"ok","champName":"janna","description":"ok"},{"type":"ok","champName":"maokai","description":"same as rell"},{"type":"ok","champName":"shaco","description":"basicly he will roam, so why not but sometimes its hard to 1v2 lane"},{"type":"ok","champName":"bard","description":"same as shaco, i only note the lane synergie so if you don't lane i can't note"},{"type":"ok","champName":"rell","description":"good cc but no damages and no range"},{"type":"low","champName":"nami","description":"don't fit well with jhin aa, not terrible"},{"type":"low","champName":"lulu","description":"bad lane, don't fit with jhin aa"},{"type":"low","champName":"milio","description":"same kind, those ones are better with hyper carry like jinx"},{"type":"low","champName":"rakan","description":"0 damages bad for jhin"},{"type":"low","champName":"renata glasc","description":"no damages, and no synergie overall"},{"type":"low","champName":"sona","description":"play seraphine"},{"type":"low","champName":"senna","description":"bad atm"},{"type":"low","champName":"zilean","description":"0 synergie with jhin"},{"type":"none","champName":"yuumi","description":"just..."},{"type":"ideal","champName":"zyra","description":"best support of all time for jhin"},{"type":"ideal","champName":"vel'koz","description":"best support atm for jhin"},{"type":"ideal","champName":"neeko","description":"also really good, she has the damages and cc you want"},{"type":"ideal","champName":"lux","description":"same as neeko, cc and damages thats what you want"},{"type":"ideal","champName":"karma","description":"peel + damage + mobility"},{"type":"ideal","champName":"pyke","description":"even if his r don't fit well with jhin, the agreesivity of thoses 2 guys is insane together, easy lane"},{"type":"ideal","champName":"xerath","description":"insane damages and range perfect for jhin"},{"type":"strong","champName":"seraphine","description":"kind of a karma, less good but insane laning"},{"type":"strong","champName":"nautilus","description":"really strong, he lack of damages but insane cc allow you to deal a lot"},{"type":"strong","champName":"blitzcrank","description":"blitz wants to have prio in lane, you are the man for this"},{"type":"strong","champName":"thresh","description":"gives you mobility and insane peel, not really agressive but same kind of nautilus good lane"},{"type":"strong","champName":"leona","description":"nice peel, nice lane"},{"type":"strong","champName":"swain","description":"good damages not the best at this job be strong"},{"type":"strong","champName":"pantheon","description":"extreme agressive, one shot every adc, but not always good can be zoned to hard by karma or this kind of champ"},{"type":"ok","champName":"soraka","description":"might lack of dmg to kill but really safe"},{"type":"ok","champName":"hwei","description":"can be strong against weak laners that you can hard poke, but not the best at the job"},{"type":"ok","champName":"morgana","description":"really confortable to play with, btw don't instant w on cages, wait 2s to click"},{"type":"ok","champName":"ashe","description":"she has slow and damages, its good but you are weak af"},{"type":"ok","champName":"taric","description":"not really good in lane but really nice in late and mid"},{"type":"ok","champName":"brand","description":"jhin needs damages but not that much, still ok"},{"type":"ok","champName":"alistar","description":"play under turret that what ali wants, not insane but good peel and dives"},{"type":"ok","champName":"camille","description":"its flip it, can be s tier or d tier depends of the enemy support but"},{"type":"ok","champName":"janna","description":"ok"},{"type":"ok","champName":"maokai","description":"same as rell"},{"type":"ok","champName":"shaco","description":"basicly he will roam, so why not but sometimes its hard to 1v2 lane"},{"type":"ok","champName":"bard","description":"same as shaco, i only note the lane synergie so if you don't lane i can't note"},{"type":"ok","champName":"rell","description":"good cc but no damages and no range"},{"type":"low","champName":"nami","description":"don't fit well with jhin aa, not terrible"},{"type":"low","champName":"lulu","description":"bad lane, don't fit with jhin aa"},{"type":"low","champName":"milio","description":"same kind, those ones are better with hyper carry like jinx"},{"type":"low","champName":"rakan","description":"0 damages bad for jhin"},{"type":"low","champName":"renata glasc","description":"no damages, and no synergie overall"},{"type":"low","champName":"sona","description":"play seraphine"},{"type":"low","champName":"senna","description":"bad atm"},{"type":"low","champName":"zilean","description":"0 synergie with jhin"},{"type":"none","champName":"yuumi","description":"just..."}],"archetype":["marksman","catcher"],"lines":[]}